AUTHORS.rst
LICENSE
README.rst
setup.py
JAX_lenstronomy.egg-info/PKG-INFO
JAX_lenstronomy.egg-info/SOURCES.txt
JAX_lenstronomy.egg-info/dependency_links.txt
JAX_lenstronomy.egg-info/requires.txt
JAX_lenstronomy.egg-info/top_level.txt
jaxtronomy/__init__.py
jaxtronomy/LensModel/__init__.py
jaxtronomy/LensModel/Profiles/__init__.py
jaxtronomy/LensModel/Profiles/p_jaffe.py
jaxtronomy/LensModel/Profiles/p_jaffe_ellipse.py
jaxtronomy/LightModel/__init__.py
jaxtronomy/LightModel/light_model.py
jaxtronomy/LightModel/light_model_base.py
jaxtronomy/LightModel/Profiles/__init__.py
jaxtronomy/LightModel/Profiles/gaussian.py
jaxtronomy/LightModel/Profiles/pixelated.py
jaxtronomy/LightModel/Profiles/sersic.py
jaxtronomy/LightModel/Profiles/uniform.py
jaxtronomy/MassModel/__init__.py
jaxtronomy/MassModel/mass_model.py
jaxtronomy/MassModel/mass_model_base.py
jaxtronomy/MassModel/Profiles/__init__.py
jaxtronomy/MassModel/Profiles/epl.py
jaxtronomy/MassModel/Profiles/gaussian_potential.py
jaxtronomy/MassModel/Profiles/multipole.py
jaxtronomy/MassModel/Profiles/nie.py
jaxtronomy/MassModel/Profiles/pixelated.py
jaxtronomy/MassModel/Profiles/point_mass.py
jaxtronomy/MassModel/Profiles/sersic_utils.py
jaxtronomy/MassModel/Profiles/shear.py
jaxtronomy/MassModel/Profiles/sie.py
jaxtronomy/MassModel/Profiles/sis.py
jaxtronomy/Util/__init__.py
jaxtronomy/Util/param_util.py
test/__init__.py
test/test_lenstronomy_import.py
test/test_LensModel/__init__.py
test/test_LensModel/test_Profiles/__init__.py
test/test_LensModel/test_Profiles/test_p_jaffe.py
test/test_LensModel/test_Profiles/test_p_jaffe_ellipse.py
test/test_Util/__init__.py
test/test_Util/test_param_util.py