Metadata-Version: 2.1
Name: JAX-lenstronomy
Version: 0.0.1rc1
Summary: lenstronomy, but in JAX
Home-page: https://github.com/lenstronomy/JAX-lenstronomy
Author: lenstronomy developers
License: BSD-3
Keywords: lenstronomy
Platform: UNKNOWN
Classifier: Development Status :: 2 - Pre-Alpha
Classifier: Intended Audience :: Science/Research
Classifier: Natural Language :: English
Classifier: Operating System :: OS Independent
Classifier: Programming Language :: Python
Classifier: Programming Language :: Python :: 3.11
License-File: LICENSE
License-File: AUTHORS.rst
